topsis_pkg/__init__.py
topsis_pkg/topsis.py
topsis_gurkirat_102303256-1.1.1.dist-info/METADATA
topsis_gurkirat_102303256-1.1.1.dist-info/WHEEL
topsis_gurkirat_102303256-1.1.1.dist-info/entry_points.txt
topsis_gurkirat_102303256-1.1.1.dist-info/top_level.txt
topsis_gurkirat_102303256-1.1.1.dist-info/RECORD
