Metadata-Version: 2.4
Name: topsis-gurkirat-102303256
Version: 1.1.1
Summary: A professional command-line tool for TOPSIS decision analysis.
Author: Gurkirat Singh
Classifier: Programming Language :: Python :: 3
Classifier: License :: OSI Approved :: MIT License
Classifier: Operating System :: OS Independent
Requires-Dist: pandas
Requires-Dist: numpy
Requires-Dist: openpyxl
Dynamic: author
Dynamic: classifier
Dynamic: description
Dynamic: description-content-type
Dynamic: requires-dist
Dynamic: summary
